efmcalculator/StateMachine.py
efmcalculator/__init__.py
efmcalculator/_version.py
efmcalculator/cli.py
efmcalculator/constants.py
efmcalculator/utilities.py
efmcalculator/data/__init__.py
efmcalculator/data/gam_df.csv
efmcalculator/ingest/EFMSequence.py
efmcalculator/ingest/__init__.py
efmcalculator/ingest/bad_state_mitigation.py
efmcalculator/ingest/parse_inputs.py
efmcalculator/pipeline/__init__.py
efmcalculator/pipeline/classify_srs_rmd.py
efmcalculator/pipeline/classify_ssr.py
efmcalculator/pipeline/detection_strats.py
efmcalculator/pipeline/features.py
efmcalculator/pipeline/filtering.py
efmcalculator/pipeline/mutation_rates.py
efmcalculator/pipeline/post_process.py
efmcalculator/pipeline/primary_pipeline.py
efmcalculator/pipeline/subsequence_curation.py
efmcalculator/webapp/SequenceState.py
efmcalculator/webapp/__init__.py
efmcalculator/webapp/bokeh_plot.py
efmcalculator/webapp/bootstrap_streamlit.py
efmcalculator/webapp/vis_utils.py
efmcalculator/webapp/webapp.py
efmcalculator/webapp/assets/favicon.ico
efmcalculator/webapp/assets/html_template.html
efmcalculator/webapp/assets/stylesheet.css
efmcalculator/webapp/assets/tombstone.ai
efmcalculator/webapp/assets/tombstone.svg
efmcalculator-0.0.post1.dist-info/licenses/LICENSE.txt
efmcalculator-0.0.post1.dist-info/METADATA
efmcalculator-0.0.post1.dist-info/WHEEL
efmcalculator-0.0.post1.dist-info/entry_points.txt
efmcalculator-0.0.post1.dist-info/top_level.txt
efmcalculator-0.0.post1.dist-info/RECORD
