Metadata-Version: 2.4
Name: EFMCalculator
Version: 0.0.post1
Summary: A webapp and command line utility for identifying mutational hotspots
Author-email: croots <croots@utexas.edu>, coolbears <sld3379@utexas.edu>, kevin99111 <kevinyang260@gmail.com>, avkatre <avyaykatre@gmail.com>
Maintainer-email: croots <croots@utexas.edu>
License: GPL-3.0
Project-URL: Homepage, https://github.com/barricklab/efmcalculator2
Project-URL: Documentation, https://github.com/barricklab/efmcalculator2
Project-URL: Issues, https://github.com/barricklab/efmcalculator2/issues
Keywords: science,biology,evolution,synthetic biology,synbio,bioinformatics,bioengineering
Classifier: Development Status :: 4 - Beta
Classifier: Environment :: Console
Classifier: Environment :: Web Environment
Classifier: Operating System :: OS Independent
Classifier: Intended Audience :: Science/Research
Classifier: License :: OSI Approved :: GNU General Public License v3 (GPLv3)
Classifier: Programming Language :: Python :: 3
Classifier: Programming Language :: Python :: 3.12
Classifier: Topic :: Scientific/Engineering :: Bio-Informatics
Requires-Python: >=3.12
License-File: LICENSE.txt
Requires-Dist: pandas
Requires-Dist: polars==1.19
Requires-Dist: progress
Requires-Dist: biopython
Requires-Dist: statsmodels
Requires-Dist: rich
Requires-Dist: pyarrow
Requires-Dist: bokeh==2.4.3
Requires-Dist: numpy<2
Requires-Dist: streamlit==1.43.0
Requires-Dist: streamlit-extras
Requires-Dist: streamlit-aggrid
Requires-Dist: streamlit_javascript
Dynamic: license-file
